zope.size-5.0-py3.11-nspkg.pth
zope/size/__init__.py
zope/size/configure.zcml
zope/size/interfaces.py
zope/size/tests.py
zope.size-5.0.dist-info/LICENSE.txt
zope.size-5.0.dist-info/METADATA
zope.size-5.0.dist-info/WHEEL
zope.size-5.0.dist-info/namespace_packages.txt
zope.size-5.0.dist-info/top_level.txt
zope.size-5.0.dist-info/RECORD
